{
  "x-api-tran-id": "P091-전금-004-P091-WALLET-KAKAO",
  "rsp_code": "00000",
  "rsp_msg": "SUCCESS",
  "next_page": null,
  "trans_cnt": 1,
  "trans_list": [
    {
      "trans_type": "04",
      "trans_num": "EP091카00008",
      "trans_dtime": "20260602182721",
      "trans_no": "WP09100001",
      "currency_code": "KRW",
      "trans_amt": -11900.0,
      "trans_org_code": "06000001",
      "trans_memo": "머니 결제",
      "merchant_name": "쿠팡이츠",
      "trans_title": "배달 결제",
      "trans_category": "식비"
    }
  ]
}