{
  "x-api-tran-id": "P102-은행-004-P102-BANK-MAIN",
  "rsp_code": "00000",
  "rsp_msg": "SUCCESS",
  "next_page": null,
  "trans_cnt": 43,
  "trans_list": [
    {
      "trans_dtime": "20260630130638",
      "trans_no": "BP10200042",
      "trans_type": "02",
      "trans_class": "계좌출금",
      "currency_code": "KRW",
      "trans_amt": -35300.0,
      "balance_amt": 2071219.0,
      "paid_in_cnt": null,
      "trans_memo": "마켓컬리"
    },
    {
      "trans_dtime": "20260630125055",
      "trans_no": "BP10200039",
      "trans_type": "02",
      "trans_class": "계좌출금",
      "currency_code": "KRW",
      "trans_amt": -22900.0,
      "balance_amt": 2191619.0,
      "paid_in_cnt": null,
      "trans_memo": "CGV"
    },
    {
      "trans_dtime": "20260629201029",
      "trans_no": "BP10200038",
      "trans_type": "02",
      "trans_class": "계좌출금",
      "currency_code": "KRW",
      "trans_amt": -14200.0,
      "balance_amt": 2214519.0,
      "paid_in_cnt": null,
      "trans_memo": "요기요"
    },
    {
      "trans_dtime": "20260629102009",
      "trans_no": "BP10200016",
      "trans_type": "02",
      "trans_class": "계좌출금",
      "currency_code": "KRW",
      "trans_amt": -38800.0,
      "balance_amt": 2920719.0,
      "paid_in_cnt": null,
      "trans_memo": "네이버쇼핑"
    },
    {
      "trans_dtime": "20260629081521",
      "trans_no": "BP10200023",
      "trans_type": "02",
      "trans_class": "계좌출금",
      "currency_code": "KRW",
      "trans_amt": -7700.0,
      "balance_amt": 2678319.0,
      "paid_in_cnt": null,
      "trans_memo": "스타벅스 합정점"
    },
    {
      "trans_dtime": "20260629081331",
      "trans_no": "BP10200014",
      "trans_type": "02",
      "trans_class": "계좌출금",
      "currency_code": "KRW",
      "trans_amt": -13500.0,
      "balance_amt": 3019019.0,
      "paid_in_cnt": null,
      "trans_memo": "배민스토어"
    },
    {
      "trans_dtime": "20260626094357",
      "trans_no": "BP10200009",
      "trans_type": "02",
      "trans_class": "내계좌이체",
      "currency_code": "KRW",
      "trans_amt": -1180000.0,
      "balance_amt": 4505719.0,
      "paid_in_cnt": null,
      "trans_memo": "적금 자동이체"
    },
    {
      "trans_dtime": "20260625215503",
      "trans_no": "BP10200015",
      "trans_type": "02",
      "trans_class": "계좌출금",
      "currency_code": "KRW",
      "trans_amt": -59500.0,
      "balance_amt": 2959519.0,
      "paid_in_cnt": null,
      "trans_memo": "네이버쇼핑"
    },
    {
      "trans_dtime": "20260625184258",
      "trans_no": "BP10200010",
      "trans_type": "02",
      "trans_class": "내계좌이체",
      "currency_code": "KRW",
      "trans_amt": -270000.0,
      "balance_amt": 4235719.0,
      "paid_in_cnt": null,
      "trans_memo": "청약 납입"
    },
    {
      "trans_dtime": "20260625091312",
      "trans_no": "BP10200006",
      "trans_type": "02",
      "trans_class": "자동이체",
      "currency_code": "KRW",
      "trans_amt": -510000.0,
      "balance_amt": 5798019.0,
      "paid_in_cnt": null,
      "trans_memo": "주거비"
    },
    {
      "trans_dtime": "20260624082858",
      "trans_no": "PAYP102",
      "trans_type": "03",
      "trans_class": "급여이체",
      "currency_code": "KRW",
      "trans_amt": 4800000.0,
      "balance_amt": 6306127.0,
      "paid_in_cnt": null,
      "trans_memo": "6월 월급"
    },
    {
      "trans_dtime": "20260622233913",
      "trans_no": "BP10200030",
      "trans_type": "02",
      "trans_class": "계좌출금",
      "currency_code": "KRW",
      "trans_amt": -59900.0,
      "balance_amt": 2478319.0,
      "paid_in_cnt": null,
      "trans_memo": "무신사"
    },
    {
      "trans_dtime": "20260622233653",
      "trans_no": "BP10200019",
      "trans_type": "02",
      "trans_class": "계좌출금",
      "currency_code": "KRW",
      "trans_amt": -143400.0,
      "balance_amt": 2749519.0,
      "paid_in_cnt": null,
      "trans_memo": "여기어때"
    },
    {
      "trans_dtime": "20260622214455",
      "trans_no": "BP10200040",
      "trans_type": "02",
      "trans_class": "계좌출금",
      "currency_code": "KRW",
      "trans_amt": -67200.0,
      "balance_amt": 2124419.0,
      "paid_in_cnt": null,
      "trans_memo": "쿠팡"
    },
    {
      "trans_dtime": "20260621181935",
      "trans_no": "BP10200004",
      "trans_type": "03",
      "trans_class": "캐시백",
      "currency_code": "KRW",
      "trans_amt": 383.0,
      "balance_amt": 6307138.0,
      "paid_in_cnt": null,
      "trans_memo": "카드 캐시백"
    },
    {
      "trans_dtime": "20260621142125",
      "trans_no": "BP10200020",
      "trans_type": "02",
      "trans_class": "계좌출금",
      "currency_code": "KRW",
      "trans_amt": -31100.0,
      "balance_amt": 2718419.0,
      "paid_in_cnt": null,
      "trans_memo": "올리브영"
    },
    {
      "trans_dtime": "20260620213403",
      "trans_no": "BP10200043",
      "trans_type": "02",
      "trans_class": "계좌출금",
      "currency_code": "KRW",
      "trans_amt": -73500.0,
      "balance_amt": 1997719.0,
      "paid_in_cnt": null,
      "trans_memo": "오늘의집"
    },
    {
      "trans_dtime": "20260620191721",
      "trans_no": "BP10200034",
      "trans_type": "02",
      "trans_class": "계좌출금",
      "currency_code": "KRW",
      "trans_amt": -46500.0,
      "balance_amt": 2347519.0,
      "paid_in_cnt": null,
      "trans_memo": "챗GPT"
    },
    {
      "trans_dtime": "20260620174348",
      "trans_no": "BP10200036",
      "trans_type": "02",
      "trans_class": "계좌출금",
      "currency_code": "KRW",
      "trans_amt": -22600.0,
      "balance_amt": 2309619.0,
      "paid_in_cnt": null,
      "trans_memo": "메가박스"
    },
    {
      "trans_dtime": "20260620135914",
      "trans_no": "BP10200018",
      "trans_type": "02",
      "trans_class": "계좌출금",
      "currency_code": "KRW",
      "trans_amt": -3500.0,
      "balance_amt": 2892919.0,
      "paid_in_cnt": null,
      "trans_memo": "던킨"
    },
    {
      "trans_dtime": "20260620091523",
      "trans_no": "BP10200008",
      "trans_type": "02",
      "trans_class": "자동이체",
      "currency_code": "KRW",
      "trans_amt": -78800.0,
      "balance_amt": 5685719.0,
      "paid_in_cnt": null,
      "trans_memo": "실손보험료"
    },
    {
      "trans_dtime": "20260619231122",
      "trans_no": "BP10200041",
      "trans_type": "02",
      "trans_class": "계좌출금",
      "currency_code": "KRW",
      "trans_amt": -17900.0,
      "balance_amt": 2106519.0,
      "paid_in_cnt": null,
      "trans_memo": "CGV"
    },
    {
      "trans_dtime": "20260619182427",
      "trans_no": "BP10200035",
      "trans_type": "02",
      "trans_class": "계좌출금",
      "currency_code": "KRW",
      "trans_amt": -15300.0,
      "balance_amt": 2332219.0,
      "paid_in_cnt": null,
      "trans_memo": "아이엠택시"
    },
    {
      "trans_dtime": "20260618174404",
      "trans_no": "BP10200002",
      "trans_type": "03",
      "trans_class": "캐시백",
      "currency_code": "KRW",
      "trans_amt": 193.0,
      "balance_amt": 6306320.0,
      "paid_in_cnt": null,
      "trans_memo": "카드 캐시백"
    },
    {
      "trans_dtime": "20260616140211",
      "trans_no": "BP10200005",
      "trans_type": "03",
      "trans_class": "캐시백",
      "currency_code": "KRW",
      "trans_amt": 881.0,
      "balance_amt": 6308019.0,
      "paid_in_cnt": null,
      "trans_memo": "카드 캐시백"
    },
    {
      "trans_dtime": "20260616122726",
      "trans_no": "BP10200013",
      "trans_type": "02",
      "trans_class": "증권이체",
      "currency_code": "KRW",
      "trans_amt": -429100.0,
      "balance_amt": 3032519.0,
      "paid_in_cnt": null,
      "trans_memo": "KODEX 200 매수"
    },
    {
      "trans_dtime": "20260616104316",
      "trans_no": "BP10200012",
      "trans_type": "02",
      "trans_class": "증권이체",
      "currency_code": "KRW",
      "trans_amt": -414100.0,
      "balance_amt": 3461619.0,
      "paid_in_cnt": null,
      "trans_memo": "KODEX 미국나스닥100TR 매수"
    },
    {
      "trans_dtime": "20260613231312",
      "trans_no": "BP10200026",
      "trans_type": "02",
      "trans_class": "계좌출금",
      "currency_code": "KRW",
      "trans_amt": -19600.0,
      "balance_amt": 2596819.0,
      "paid_in_cnt": null,
      "trans_memo": "우티"
    },
    {
      "trans_dtime": "20260613193449",
      "trans_no": "BP10200032",
      "trans_type": "02",
      "trans_class": "계좌출금",
      "currency_code": "KRW",
      "trans_amt": -3700.0,
      "balance_amt": 2415019.0,
      "paid_in_cnt": null,
      "trans_memo": "파리바게뜨"
    },
    {
      "trans_dtime": "20260613101651",
      "trans_no": "BP10200037",
      "trans_type": "02",
      "trans_class": "계좌출금",
      "currency_code": "KRW",
      "trans_amt": -80900.0,
      "balance_amt": 2228719.0,
      "paid_in_cnt": null,
      "trans_memo": "무신사"
    },
    {
      "trans_dtime": "20260613100459",
      "trans_no": "BP10200007",
      "trans_type": "02",
      "trans_class": "자동이체",
      "currency_code": "KRW",
      "trans_amt": -33500.0,
      "balance_amt": 5764519.0,
      "paid_in_cnt": null,
      "trans_memo": "구독 서비스"
    },
    {
      "trans_dtime": "20260610235037",
      "trans_no": "BP10200021",
      "trans_type": "02",
      "trans_class": "계좌출금",
      "currency_code": "KRW",
      "trans_amt": -28800.0,
      "balance_amt": 2689619.0,
      "paid_in_cnt": null,
      "trans_memo": "쿠팡"
    },
    {
      "trans_dtime": "20260610203046",
      "trans_no": "BP10200017",
      "trans_type": "02",
      "trans_class": "계좌출금",
      "currency_code": "KRW",
      "trans_amt": -24300.0,
      "balance_amt": 2896419.0,
      "paid_in_cnt": null,
      "trans_memo": "김밥천국 홍대점"
    },
    {
      "trans_dtime": "20260610111545",
      "trans_no": "BP10200027",
      "trans_type": "02",
      "trans_class": "계좌출금",
      "currency_code": "KRW",
      "trans_amt": -19000.0,
      "balance_amt": 2577819.0,
      "paid_in_cnt": null,
      "trans_memo": "아모레몰"
    },
    {
      "trans_dtime": "20260610082610",
      "trans_no": "BP10200011",
      "trans_type": "02",
      "trans_class": "내계좌이체",
      "currency_code": "KRW",
      "trans_amt": -360000.0,
      "balance_amt": 3875719.0,
      "paid_in_cnt": null,
      "trans_memo": "비상금 이체"
    },
    {
      "trans_dtime": "20260610070846",
      "trans_no": "BP10200024",
      "trans_type": "02",
      "trans_class": "계좌출금",
      "currency_code": "KRW",
      "trans_amt": -6900.0,
      "balance_amt": 2671419.0,
      "paid_in_cnt": null,
      "trans_memo": "서울교통공사"
    },
    {
      "trans_dtime": "20260609110119",
      "trans_no": "BP10200003",
      "trans_type": "03",
      "trans_class": "캐시백",
      "currency_code": "KRW",
      "trans_amt": 435.0,
      "balance_amt": 6306755.0,
      "paid_in_cnt": null,
      "trans_memo": "카드 캐시백"
    },
    {
      "trans_dtime": "20260606204839",
      "trans_no": "BP10200022",
      "trans_type": "02",
      "trans_class": "계좌출금",
      "currency_code": "KRW",
      "trans_amt": -3600.0,
      "balance_amt": 2686019.0,
      "paid_in_cnt": null,
      "trans_memo": "노티드"
    },
    {
      "trans_dtime": "20260604173131",
      "trans_no": "BP10200029",
      "trans_type": "02",
      "trans_class": "계좌출금",
      "currency_code": "KRW",
      "trans_amt": -21100.0,
      "balance_amt": 2538219.0,
      "paid_in_cnt": null,
      "trans_memo": "알라딘"
    },
    {
      "trans_dtime": "20260603225827",
      "trans_no": "BP10200025",
      "trans_type": "02",
      "trans_class": "계좌출금",
      "currency_code": "KRW",
      "trans_amt": -55000.0,
      "balance_amt": 2616419.0,
      "paid_in_cnt": null,
      "trans_memo": "유튜브 프리미엄"
    },
    {
      "trans_dtime": "20260603212744",
      "trans_no": "BP10200033",
      "trans_type": "02",
      "trans_class": "계좌출금",
      "currency_code": "KRW",
      "trans_amt": -21000.0,
      "balance_amt": 2394019.0,
      "paid_in_cnt": null,
      "trans_memo": "담소소사골순대"
    },
    {
      "trans_dtime": "20260602120221",
      "trans_no": "BP10200031",
      "trans_type": "02",
      "trans_class": "계좌출금",
      "currency_code": "KRW",
      "trans_amt": -59600.0,
      "balance_amt": 2418719.0,
      "paid_in_cnt": null,
      "trans_memo": "오늘의집"
    },
    {
      "trans_dtime": "20260602110320",
      "trans_no": "BP10200028",
      "trans_type": "02",
      "trans_class": "계좌출금",
      "currency_code": "KRW",
      "trans_amt": -18500.0,
      "balance_amt": 2559319.0,
      "paid_in_cnt": null,
      "trans_memo": "주식회사 우아한형제들"
    }
  ]
}