{
  "x-api-tran-id": "P145-은행-004-P145-BANK-MAIN",
  "rsp_code": "00000",
  "rsp_msg": "SUCCESS",
  "next_page": null,
  "trans_cnt": 34,
  "trans_list": [
    {
      "trans_dtime": "20260630203058",
      "trans_no": "BP14500017",
      "trans_type": "02",
      "trans_class": "계좌출금",
      "currency_code": "KRW",
      "trans_amt": -59400.0,
      "balance_amt": 4324211.0,
      "paid_in_cnt": null,
      "trans_memo": "GS25"
    },
    {
      "trans_dtime": "20260630124334",
      "trans_no": "BP14500016",
      "trans_type": "02",
      "trans_class": "계좌출금",
      "currency_code": "KRW",
      "trans_amt": -27200.0,
      "balance_amt": 4383611.0,
      "paid_in_cnt": null,
      "trans_memo": "김밥천국 홍대점"
    },
    {
      "trans_dtime": "20260629201304",
      "trans_no": "BP14500013",
      "trans_type": "02",
      "trans_class": "계좌출금",
      "currency_code": "KRW",
      "trans_amt": -10500.0,
      "balance_amt": 4498611.0,
      "paid_in_cnt": null,
      "trans_memo": "노티드"
    },
    {
      "trans_dtime": "20260629084645",
      "trans_no": "BP14500032",
      "trans_type": "02",
      "trans_class": "계좌출금",
      "currency_code": "KRW",
      "trans_amt": -22300.0,
      "balance_amt": 3467511.0,
      "paid_in_cnt": null,
      "trans_memo": "요기요"
    },
    {
      "trans_dtime": "20260628124824",
      "trans_no": "BP14500008",
      "trans_type": "02",
      "trans_class": "내계좌이체",
      "currency_code": "KRW",
      "trans_amt": -210000.0,
      "balance_amt": 4840311.0,
      "paid_in_cnt": null,
      "trans_memo": "적금 자동이체"
    },
    {
      "trans_dtime": "20260628110417",
      "trans_no": "BP14500010",
      "trans_type": "02",
      "trans_class": "내계좌이체",
      "currency_code": "KRW",
      "trans_amt": -70000.0,
      "balance_amt": 4720311.0,
      "paid_in_cnt": null,
      "trans_memo": "비상금 이체"
    },
    {
      "trans_dtime": "20260628080441",
      "trans_no": "BP14500018",
      "trans_type": "02",
      "trans_class": "계좌출금",
      "currency_code": "KRW",
      "trans_amt": -12800.0,
      "balance_amt": 4311411.0,
      "paid_in_cnt": null,
      "trans_memo": "티머니"
    },
    {
      "trans_dtime": "20260626230747",
      "trans_no": "BP14500021",
      "trans_type": "02",
      "trans_class": "계좌출금",
      "currency_code": "KRW",
      "trans_amt": -75200.0,
      "balance_amt": 4141811.0,
      "paid_in_cnt": null,
      "trans_memo": "쿠팡"
    },
    {
      "trans_dtime": "20260626122309",
      "trans_no": "BP14500027",
      "trans_type": "02",
      "trans_class": "계좌출금",
      "currency_code": "KRW",
      "trans_amt": -5400.0,
      "balance_amt": 3806511.0,
      "paid_in_cnt": null,
      "trans_memo": "이디야커피"
    },
    {
      "trans_dtime": "20260626083643",
      "trans_no": "PAYP145",
      "trans_type": "03",
      "trans_class": "급여이체",
      "currency_code": "KRW",
      "trans_amt": 3890000.0,
      "balance_amt": 6078530.0,
      "paid_in_cnt": null,
      "trans_memo": "6월 월급"
    },
    {
      "trans_dtime": "20260622081423",
      "trans_no": "BP14500033",
      "trans_type": "02",
      "trans_class": "계좌출금",
      "currency_code": "KRW",
      "trans_amt": -6300.0,
      "balance_amt": 3461211.0,
      "paid_in_cnt": null,
      "trans_memo": "컴포즈커피"
    },
    {
      "trans_dtime": "20260621193855",
      "trans_no": "BP14500025",
      "trans_type": "02",
      "trans_class": "계좌출금",
      "currency_code": "KRW",
      "trans_amt": -11100.0,
      "balance_amt": 3910911.0,
      "paid_in_cnt": null,
      "trans_memo": "우티"
    },
    {
      "trans_dtime": "20260620135613",
      "trans_no": "BP14500028",
      "trans_type": "02",
      "trans_class": "계좌출금",
      "currency_code": "KRW",
      "trans_amt": -20200.0,
      "balance_amt": 3786311.0,
      "paid_in_cnt": null,
      "trans_memo": "주식회사 우아한형제들"
    },
    {
      "trans_dtime": "20260618083429",
      "trans_no": "BP14500034",
      "trans_type": "02",
      "trans_class": "계좌출금",
      "currency_code": "KRW",
      "trans_amt": -19400.0,
      "balance_amt": 3441811.0,
      "paid_in_cnt": null,
      "trans_memo": "요기요"
    },
    {
      "trans_dtime": "20260618082522",
      "trans_no": "BP14500020",
      "trans_type": "02",
      "trans_class": "계좌출금",
      "currency_code": "KRW",
      "trans_amt": -33800.0,
      "balance_amt": 4217011.0,
      "paid_in_cnt": null,
      "trans_memo": "한솥도시락 신촌점"
    },
    {
      "trans_dtime": "20260617212209",
      "trans_no": "BP14500031",
      "trans_type": "02",
      "trans_class": "계좌출금",
      "currency_code": "KRW",
      "trans_amt": -71600.0,
      "balance_amt": 3489811.0,
      "paid_in_cnt": null,
      "trans_memo": "네이버쇼핑"
    },
    {
      "trans_dtime": "20260617210913",
      "trans_no": "BP14500026",
      "trans_type": "02",
      "trans_class": "계좌출금",
      "currency_code": "KRW",
      "trans_amt": -99000.0,
      "balance_amt": 3811911.0,
      "paid_in_cnt": null,
      "trans_memo": "멜론"
    },
    {
      "trans_dtime": "20260616221334",
      "trans_no": "BP14500023",
      "trans_type": "02",
      "trans_class": "계좌출금",
      "currency_code": "KRW",
      "trans_amt": -68200.0,
      "balance_amt": 4006211.0,
      "paid_in_cnt": null,
      "trans_memo": "이마트"
    },
    {
      "trans_dtime": "20260615215737",
      "trans_no": "BP14500019",
      "trans_type": "02",
      "trans_class": "계좌출금",
      "currency_code": "KRW",
      "trans_amt": -60600.0,
      "balance_amt": 4250811.0,
      "paid_in_cnt": null,
      "trans_memo": "알라딘"
    },
    {
      "trans_dtime": "20260615195224",
      "trans_no": "BP14500006",
      "trans_type": "02",
      "trans_class": "자동이체",
      "currency_code": "KRW",
      "trans_amt": -27500.0,
      "balance_amt": 5130611.0,
      "paid_in_cnt": null,
      "trans_memo": "추가 구독 서비스"
    },
    {
      "trans_dtime": "20260615154159",
      "trans_no": "BP14500007",
      "trans_type": "02",
      "trans_class": "자동이체",
      "currency_code": "KRW",
      "trans_amt": -80300.0,
      "balance_amt": 5050311.0,
      "paid_in_cnt": null,
      "trans_memo": "실손보험료"
    },
    {
      "trans_dtime": "20260613234744",
      "trans_no": "BP14500022",
      "trans_type": "02",
      "trans_class": "계좌출금",
      "currency_code": "KRW",
      "trans_amt": -67400.0,
      "balance_amt": 4074411.0,
      "paid_in_cnt": null,
      "trans_memo": "인터파크티켓"
    },
    {
      "trans_dtime": "20260613203018",
      "trans_no": "BP14500029",
      "trans_type": "02",
      "trans_class": "계좌출금",
      "currency_code": "KRW",
      "trans_amt": -77500.0,
      "balance_amt": 3708811.0,
      "paid_in_cnt": null,
      "trans_memo": "11번가"
    },
    {
      "trans_dtime": "20260613154441",
      "trans_no": "BP14500012",
      "trans_type": "02",
      "trans_class": "증권이체",
      "currency_code": "KRW",
      "trans_amt": -115100.0,
      "balance_amt": 4509111.0,
      "paid_in_cnt": null,
      "trans_memo": "TIGER 미국나스닥100 매수"
    },
    {
      "trans_dtime": "20260611210758",
      "trans_no": "BP14500005",
      "trans_type": "02",
      "trans_class": "자동이체",
      "currency_code": "KRW",
      "trans_amt": -91800.0,
      "balance_amt": 5158111.0,
      "paid_in_cnt": null,
      "trans_memo": "휴대폰 요금"
    },
    {
      "trans_dtime": "20260611111714",
      "trans_no": "BP14500003",
      "trans_type": "03",
      "trans_class": "캐시백",
      "currency_code": "KRW",
      "trans_amt": 868.0,
      "balance_amt": 6079911.0,
      "paid_in_cnt": null,
      "trans_memo": "카드 캐시백"
    },
    {
      "trans_dtime": "20260610161127",
      "trans_no": "BP14500030",
      "trans_type": "02",
      "trans_class": "계좌출금",
      "currency_code": "KRW",
      "trans_amt": -147400.0,
      "balance_amt": 3561411.0,
      "paid_in_cnt": null,
      "trans_memo": "지그재그"
    },
    {
      "trans_dtime": "20260609092257",
      "trans_no": "BP14500002",
      "trans_type": "03",
      "trans_class": "캐시백",
      "currency_code": "KRW",
      "trans_amt": 513.0,
      "balance_amt": 6079043.0,
      "paid_in_cnt": null,
      "trans_memo": "카드 캐시백"
    },
    {
      "trans_dtime": "20260603162543",
      "trans_no": "BP14500009",
      "trans_type": "02",
      "trans_class": "내계좌이체",
      "currency_code": "KRW",
      "trans_amt": -50000.0,
      "balance_amt": 4790311.0,
      "paid_in_cnt": null,
      "trans_memo": "청약 납입"
    },
    {
      "trans_dtime": "20260602194423",
      "trans_no": "BP14500015",
      "trans_type": "02",
      "trans_class": "계좌출금",
      "currency_code": "KRW",
      "trans_amt": -8100.0,
      "balance_amt": 4410811.0,
      "paid_in_cnt": null,
      "trans_memo": "배스킨라빈스"
    },
    {
      "trans_dtime": "20260602122425",
      "trans_no": "BP14500011",
      "trans_type": "02",
      "trans_class": "증권이체",
      "currency_code": "KRW",
      "trans_amt": -96100.0,
      "balance_amt": 4624211.0,
      "paid_in_cnt": null,
      "trans_memo": "카카오 매수"
    },
    {
      "trans_dtime": "20260602120303",
      "trans_no": "BP14500024",
      "trans_type": "02",
      "trans_class": "계좌출금",
      "currency_code": "KRW",
      "trans_amt": -84200.0,
      "balance_amt": 3922011.0,
      "paid_in_cnt": null,
      "trans_memo": "무신사"
    },
    {
      "trans_dtime": "20260602094322",
      "trans_no": "BP14500004",
      "trans_type": "02",
      "trans_class": "자동이체",
      "currency_code": "KRW",
      "trans_amt": -830000.0,
      "balance_amt": 5249911.0,
      "paid_in_cnt": null,
      "trans_memo": "주거비"
    },
    {
      "trans_dtime": "20260601134042",
      "trans_no": "BP14500014",
      "trans_type": "02",
      "trans_class": "계좌출금",
      "currency_code": "KRW",
      "trans_amt": -79700.0,
      "balance_amt": 4418911.0,
      "paid_in_cnt": null,
      "trans_memo": "유튜브 프리미엄"
    }
  ]
}